ttidle/__init__.py
ttidle/__main__.py
ttidle/cli.py
tt_idle-0.3.0.dist-info/METADATA
tt_idle-0.3.0.dist-info/WHEEL
tt_idle-0.3.0.dist-info/entry_points.txt
tt_idle-0.3.0.dist-info/RECORD
