Metadata-Version: 2.4
Name: tt-idle
Version: 0.3.0
Summary: Add your description here
Requires-Python: >=3.13
Requires-Dist: humanfriendly>=10.0
Requires-Dist: keyboard>=0.13.5
